pydebugvisualizer/__init__.py
pydebugvisualizer/visualize.py
pydebugvisualizer/detection/__init__.py
pydebugvisualizer/detection/structure_analyzer.py
pydebugvisualizer/extractors/__init__.py
pydebugvisualizer/extractors/base.py
pydebugvisualizer/extractors/builtin.py
pydebugvisualizer/extractors/custom.py
pydebugvisualizer/extractors/matplotlib_ext.py
pydebugvisualizer/extractors/numpy_ext.py
pydebugvisualizer/extractors/pandas_ext.py
pydebugvisualizer/extractors/registry.py
pydebugvisualizer/extractors/structure_ext.py
pydebugvisualizer-0.1.0.dist-info/METADATA
pydebugvisualizer-0.1.0.dist-info/WHEEL
pydebugvisualizer-0.1.0.dist-info/top_level.txt
pydebugvisualizer-0.1.0.dist-info/RECORD
