Metadata-Version: 2.4
Name: pydebugvisualizer
Version: 0.1.0
Summary: Python Debug Visualizer - Automatic data structure visualization for VS Code debugging
Author-email: Vignesh Karnika <your-email@example.com>
License: MIT
Project-URL: Homepage, https://github.com/vkfolio/python-debug-visualizer
Project-URL: Repository, https://github.com/vkfolio/python-debug-visualizer
Project-URL: Issues, https://github.com/vkfolio/python-debug-visualizer/issues
Classifier: Development Status :: 3 - Alpha
Classifier: Intended Audience :: Developers
Classifier: License :: OSI Approved :: MIT License
Classifier: Programming Language :: Python :: 3
Classifier: Programming Language :: Python :: 3.8
Classifier: Programming Language :: Python :: 3.9
Classifier: Programming Language :: Python :: 3.10
Classifier: Programming Language :: Python :: 3.11
Classifier: Programming Language :: Python :: 3.12
Classifier: Topic :: Software Development :: Debuggers
Requires-Python: >=3.8
Provides-Extra: numpy
Requires-Dist: numpy>=1.20.0; extra == "numpy"
Provides-Extra: pandas
Requires-Dist: pandas>=1.3.0; extra == "pandas"
Provides-Extra: matplotlib
Requires-Dist: matplotlib>=3.4.0; extra == "matplotlib"
Provides-Extra: datascience
Requires-Dist: numpy>=1.20.0; extra == "datascience"
Requires-Dist: pandas>=1.3.0; extra == "datascience"
Requires-Dist: matplotlib>=3.4.0; extra == "datascience"
Provides-Extra: dev
Requires-Dist: pytest>=7.0.0; extra == "dev"
Requires-Dist: pytest-cov>=4.0.0; extra == "dev"
Requires-Dist: black>=23.0.0; extra == "dev"
Requires-Dist: mypy>=1.0.0; extra == "dev"
